COPYING
README.rst
htail.py
setup.py
htail.egg-info/PKG-INFO
htail.egg-info/SOURCES.txt
htail.egg-info/dependency_links.txt
htail.egg-info/entry_points.txt
htail.egg-info/top_level.txt
htail.egg-info/zip-safe